setup.py
src/duckietown_messages/__init__.py
src/duckietown_messages/base.py
src/duckietown_messages.egg-info/PKG-INFO
src/duckietown_messages.egg-info/SOURCES.txt
src/duckietown_messages.egg-info/dependency_links.txt
src/duckietown_messages.egg-info/requires.txt
src/duckietown_messages.egg-info/top_level.txt
src/duckietown_messages/actuators/__init__.py
src/duckietown_messages/actuators/attitude_pids_parameters.py
src/duckietown_messages/actuators/car_lights.py
src/duckietown_messages/actuators/dc_motor.py
src/duckietown_messages/actuators/differential_pwm.py
src/duckietown_messages/actuators/display_fragment.py
src/duckietown_messages/actuators/display_fragments.py
src/duckietown_messages/actuators/drone_control.py
src/duckietown_messages/actuators/drone_mode.py
src/duckietown_messages/actuators/drone_motor_command.py
src/duckietown_messages/actuators/generic.py
src/duckietown_messages/actuators/leds.py
src/duckietown_messages/calibrations/__init__.py
src/duckietown_messages/calibrations/camera_extrinsic.py
src/duckietown_messages/calibrations/camera_intrinsic.py
src/duckietown_messages/calibrations/dc_motor.py
src/duckietown_messages/colors/__init__.py
src/duckietown_messages/colors/rgb.py
src/duckietown_messages/colors/rgba.py
src/duckietown_messages/geometry_2d/__init__.py
src/duckietown_messages/geometry_2d/homography.py
src/duckietown_messages/geometry_2d/point.py
src/duckietown_messages/geometry_2d/roi.py
src/duckietown_messages/geometry_3d/__init__.py
src/duckietown_messages/geometry_3d/position.py
src/duckietown_messages/geometry_3d/quaternion.py
src/duckietown_messages/geometry_3d/transformation.py
src/duckietown_messages/geometry_3d/twist.py
src/duckietown_messages/geometry_3d/vector.py
src/duckietown_messages/network/__init__.py
src/duckietown_messages/network/dtps/__init__.py
src/duckietown_messages/network/dtps/context.py
src/duckietown_messages/sensors/__init__.py
src/duckietown_messages/sensors/angular_velocities.py
src/duckietown_messages/sensors/battery.py
src/duckietown_messages/sensors/button_event.py
src/duckietown_messages/sensors/camera.py
src/duckietown_messages/sensors/compressed_image.py
src/duckietown_messages/sensors/generic.py
