Metadata-Version: 2.1
Name: duckietown-messages
Version: 0.0.24
Home-page: https://github.com/duckietown/duckietown-messages
Author: Andrea F. Daniele
Author-email: afdaniele@duckietown.com
Requires-Dist: pydantic
Requires-Dist: numpy
Requires-Dist: pyturbojpeg
Requires-Dist: Pillow
Requires-Dist: pytransform3d
